README.md
setup.py
pyledgerqrl/__init__.py
pyledgerqrl/ledgerqrl.py
pyledgerqrl.egg-info/PKG-INFO
pyledgerqrl.egg-info/SOURCES.txt
pyledgerqrl.egg-info/dependency_links.txt
pyledgerqrl.egg-info/not-zip-safe
pyledgerqrl.egg-info/requires.txt
pyledgerqrl.egg-info/top_level.txt