Metadata-Version: 1.0
Name: pyledgerqrl
Version: 0.5.1
Summary: python module for Ledger Nano S
Home-page: https://github.com/theQRL/ledger-qrl
Author: The QRL Team
Author-email: info@theqrl.org
License: MIT
Platform: UNKNOWN
